Metadata-Version: 2.1
Name: owens-library
Version: 0.0.1
Summary: A very basic calculator
Home-page: 
Author: Owen Abraham
Author-email: picket_0bakcups@icloud.com
License: MIT
Keywords: calculator
Classifier: Development Status :: 5 - Production/Stable
Classifier: Intended Audience :: Education
Classifier: Operating System :: Microsoft :: Windows :: Windows 10
Classifier: License :: OSI Approved :: MIT License
Classifier: Programming Language :: Python :: 3
License-File: LICENSE.txt
